xenvman/__init__.py
xenvman/client.py
xenvman/env.py
xenvman/errors.py
xenvman/types.py
xenvman-0.0.1.dist-info/LICENSE
xenvman-0.0.1.dist-info/METADATA
xenvman-0.0.1.dist-info/WHEEL
xenvman-0.0.1.dist-info/top_level.txt
xenvman-0.0.1.dist-info/RECORD
