Metadata-Version: 2.1
Name: xenvman
Version: 0.0.1
Summary: xenvman client for Python
Home-page: https://github.com/syhpoon/xenvman
Author: Max Kuznetsov
Author-email: syhpoon@syhpoon.ca
License: UNKNOWN
Platform: UNKNOWN
Classifier: Programming Language :: Python :: 3
Classifier: License :: OSI Approved :: MIT License
Classifier: Operating System :: OS Independent
Requires-Python: >=3
Requires-Dist: requests
